aioworkers_aiohttp/__init__.py
aioworkers_aiohttp/abc.py
aioworkers_aiohttp/app.py
aioworkers_aiohttp/plugin.ini
aioworkers_aiohttp/router.py
aioworkers_aiohttp/server.py
aioworkers_aiohttp/storage.py
aioworkers_aiohttp/supervisor.py
aioworkers_aiohttp-0.8.dist-info/METADATA
aioworkers_aiohttp-0.8.dist-info/WHEEL
aioworkers_aiohttp-0.8.dist-info/entry_points.txt
aioworkers_aiohttp-0.8.dist-info/licenses/LICENSE
aioworkers_aiohttp-0.8.dist-info/RECORD
